README.rst
setup.py
pyalgs/__init__.py
pyalgs.egg-info/PKG-INFO
pyalgs.egg-info/SOURCES.txt
pyalgs.egg-info/dependency_links.txt
pyalgs.egg-info/not-zip-safe
pyalgs.egg-info/top_level.txt