Metadata-Version: 1.1
Name: pyalgs
Version: 0.0.1
Summary: Python implementation of Robert Sedgwick's Algorithm (Part I and Part II) Coursera course
Home-page: https://github.com/chen0040/pyalgs
Author: Xianshun Chen
Author-email: xs0040@gmail.com
License: BSD
Platform: any
Classifier: License :: OSI Approved :: BSD License
Classifier: Operating System :: OS Independent
Classifier: Natural Language :: English
Classifier: Programming Language :: Python
Classifier: Programming Language :: Python :: 2
Classifier: Programming Language :: Python :: 2.7
Classifier: Programming Language :: Python :: 3
Classifier: Programming Language :: Python :: 3.3
Classifier: Programming Language :: Python :: 3.4
Classifier: Programming Language :: Python :: 3.5
Classifier: Topic :: Text Processing :: General
Classifier: Topic :: Utilities
Classifier: Intended Audience :: Developers
Classifier: Intended Audience :: Education
Classifier: Intended Audience :: Science/Research
Classifier: Topic :: Software Development :: Libraries :: Python Modules
